{
  "meta": {
    "source": "Practical Fishkeeping",
    "sourceUrl": "https://www.practicalfishkeeping.co.uk/",
    "accessedDate": "2026-06-08",
    "slice": "fish-freshwater"
  },
  "entries": [
    {
      "commonName": "Cardinal Tetra",
      "scientificName": "Paracheirodon axelrodi",
      "categoryGroup": "tetra",
      "articleUrl": "https://www.practicalfishkeeping.co.uk/features/cardinal-tetra-paracheirodon-axelrodi/",
      "imageUrl": null,
      "uniqueAngle": "PFK dedicated species profile; Rio Negro origin, soft/acidic water requirements",
      "notes": null
    },
    {
      "commonName": "Neon Tetra",
      "scientificName": "Paracheirodon innesi",
      "categoryGroup": "tetra",
      "articleUrl": "https://www.practicalfishkeeping.co.uk/features/12-great-community-tank-tetras/",
      "imageUrl": null,
      "uniqueAngle": "UK community tank staple, PFK covers as benchmark community species",
      "notes": null
    },
    {
      "commonName": "Ember Tetra",
      "scientificName": "Hyphessobrycon amandae",
      "categoryGroup": "tetra",
      "articleUrl": "https://www.practicalfishkeeping.co.uk/features/12-great-community-tank-tetras/",
      "imageUrl": null,
      "uniqueAngle": "PFK community tetra feature; popular nano species in UK trade",
      "notes": null
    },
    {
      "commonName": "Lemon Tetra",
      "scientificName": "Hyphessobrycon pulchripinnis",
      "categoryGroup": "tetra",
      "articleUrl": "https://www.practicalfishkeeping.co.uk/features/community-tetras-alternatives-to-butter/",
      "imageUrl": null,
      "uniqueAngle": "PFK 'alternatives to butter' community tetra feature",
      "notes": null
    },
    {
      "commonName": "Emperor Tetra",
      "scientificName": "Nematobrycon palmeri",
      "categoryGroup": "tetra",
      "articleUrl": "https://www.practicalfishkeeping.co.uk/features/community-tetras-alternatives-to-butter/",
      "imageUrl": null,
      "uniqueAngle": "Hard water tolerant tetra noted in PFK UK hard-water tank guide",
      "notes": null
    },
    {
      "commonName": "Bleeding Heart Tetra",
      "scientificName": "Hyphessobrycon erythrostigma",
      "categoryGroup": "tetra",
      "articleUrl": "https://www.practicalfishkeeping.co.uk/features/community-tetras-alternatives-to-butter/",
      "imageUrl": null,
      "uniqueAngle": "PFK community tetra feature",
      "notes": null
    },
    {
      "commonName": "Red-eye Tetra",
      "scientificName": "Moenkhausia sanctaefilomenae",
      "categoryGroup": "tetra",
      "articleUrl": "https://www.practicalfishkeeping.co.uk/features/community-tetras-alternatives-to-butter/",
      "imageUrl": null,
      "uniqueAngle": "Tolerant of hard water; PFK community tetra recommendation",
      "notes": null
    },
    {
      "commonName": "Bucktooth Tetra",
      "scientificName": "Exodon paradoxus",
      "categoryGroup": "tetra",
      "articleUrl": "https://www.practicalfishkeeping.co.uk/features/predators-the-bucktooth-tetra/",
      "imageUrl": null,
      "uniqueAngle": "PFK predator feature; scale-eating specialist, species-only tank",
      "notes": null
    },
    {
      "commonName": "Rathbun's Tetra",
      "scientificName": "Hyphessobrycon rathbuni",
      "categoryGroup": "tetra",
      "articleUrl": "https://www.practicalfishkeeping.co.uk/features/rathbuns-tetra-in-the-wild/",
      "imageUrl": null,
      "uniqueAngle": "PFK wild-collected field report; UK gap-filler, rarely covered in US press",
      "notes": null
    },
    {
      "commonName": "Brittanichthys Tetra",
      "scientificName": "Brittanichthys axelrodi",
      "categoryGroup": "tetra",
      "articleUrl": "https://www.practicalfishkeeping.co.uk/features/brittanichthys-axelrodi/",
      "imageUrl": null,
      "uniqueAngle": "PFK species profile; unusual Rio Negro characiform, rare in US trade",
      "notes": null
    },
    {
      "commonName": "Cenepa Red Pencilfish",
      "scientificName": "Nannostomus sp. 'Cenepa Red'",
      "categoryGroup": "pencilfish",
      "articleUrl": "https://www.practicalfishkeeping.co.uk/features/cenepa-red-pencilfish/",
      "imageUrl": null,
      "uniqueAngle": "PFK new-to-hobby species feature; Rio Morona blackwater tributary, UK import news",
      "notes": "Undescribed at time of PFK coverage; blackwater pencilfish not commonly seen in US trade"
    },
    {
      "commonName": "Hockey Stick Pencilfish",
      "scientificName": "Nannostomus eques",
      "categoryGroup": "pencilfish",
      "articleUrl": "https://www.practicalfishkeeping.co.uk/features/12-great-community-tank-tetras/",
      "imageUrl": null,
      "uniqueAngle": "PFK recommended community nano species",
      "notes": null
    },
    {
      "commonName": "Shining Pencilfish",
      "scientificName": "Nannostomus nitidus",
      "categoryGroup": "pencilfish",
      "articleUrl": "https://www.practicalfishkeeping.co.uk/features/how-to-keep-darter-characins/",
      "imageUrl": null,
      "uniqueAngle": "UK trade gap-filler; PFK species mention",
      "notes": null
    },
    {
      "commonName": "Silver Hatchetfish",
      "scientificName": "Gasteropelecus sternicla",
      "categoryGroup": "hatchetfish",
      "articleUrl": "https://www.practicalfishkeeping.co.uk/features/why-hatchetfish-tick-all-the-right-boxes/",
      "imageUrl": null,
      "uniqueAngle": "PFK dedicated hatchetfish feature",
      "notes": null
    },
    {
      "commonName": "Marbled Hatchetfish",
      "scientificName": "Carnegiella strigata",
      "categoryGroup": "hatchetfish",
      "articleUrl": "https://www.practicalfishkeeping.co.uk/features/why-hatchetfish-tick-all-the-right-boxes/",
      "imageUrl": null,
      "uniqueAngle": "PFK hatchetfish feature; Carnegiella genus profiled",
      "notes": null
    },
    {
      "commonName": "Black-winged Hatchetfish",
      "scientificName": "Carnegiella marthae",
      "categoryGroup": "hatchetfish",
      "articleUrl": "https://www.practicalfishkeeping.co.uk/fishkeeping-news/black-winged-hatchetfish-not-one-but-three-species/",
      "imageUrl": null,
      "uniqueAngle": "PFK news item on cryptic species split; now recognised as three species",
      "notes": "Genetic study confirmed C. marthae actually comprises three species"
    },
    {
      "commonName": "Striped Pike Characin",
      "scientificName": "Boulengerella lateristriga",
      "categoryGroup": "pike-characin",
      "articleUrl": "https://www.practicalfishkeeping.co.uk/features/predators-the-striped-pike-characin/",
      "imageUrl": null,
      "uniqueAngle": "PFK predator series; UK trade oddity rarely covered in US hobby press",
      "notes": null
    },
    {
      "commonName": "Red Wolf Fish",
      "scientificName": "Erythrinus erythrinus",
      "categoryGroup": "wolf-fish",
      "articleUrl": "https://www.practicalfishkeeping.co.uk/features/red-wolf-fish-erythrinus-erythrinus/",
      "imageUrl": null,
      "uniqueAngle": "PFK species profile; UK-available predator with dedicated care article",
      "notes": null
    },
    {
      "commonName": "Payara / Vampire Tetra",
      "scientificName": "Hydrolycus scomberoides",
      "categoryGroup": "vampire-fish",
      "articleUrl": "https://www.practicalfishkeeping.co.uk/features/hydrolycus-scomberoides/",
      "imageUrl": null,
      "uniqueAngle": "PFK dedicated species profile; extreme predator, specialist UK import",
      "notes": null
    },
    {
      "commonName": "Wolf Fish",
      "scientificName": "Hoplias malabaricus",
      "categoryGroup": "wolf-fish",
      "articleUrl": "https://www.practicalfishkeeping.co.uk/features/predators-hoplias-wolves-of-the-water/",
      "imageUrl": null,
      "uniqueAngle": "PFK predator series; UK-available South American predator",
      "notes": null
    },
    {
      "commonName": "Darter Characin",
      "scientificName": "Characidium sp.",
      "categoryGroup": "darter-characin",
      "articleUrl": "https://www.practicalfishkeeping.co.uk/features/how-to-keep-darter-characins/",
      "imageUrl": null,
      "uniqueAngle": "PFK dedicated care guide; underrepresented group in US trade resources",
      "notes": null
    },
    {
      "commonName": "Black Ruby Barb",
      "scientificName": "Pethia nigrofasciata",
      "categoryGroup": "barb",
      "articleUrl": "https://www.practicalfishkeeping.co.uk/features/behold-black-rubies/",
      "imageUrl": null,
      "uniqueAngle": "PFK dedicated feature 'Behold Black Rubies!'; popular UK trade species",
      "notes": null
    },
    {
      "commonName": "Red-lined Torpedo Barb",
      "scientificName": "Dawkinsia denisonii",
      "categoryGroup": "barb",
      "articleUrl": "https://www.practicalfishkeeping.co.uk/features/red-lined-torpedo-barb-puntius-denisonii/",
      "imageUrl": null,
      "uniqueAngle": "PFK dedicated species guide; UK trade name Denison barb",
      "notes": "Formerly Puntius denisonii; flagship large barb in UK trade"
    },
    {
      "commonName": "Tiger Barb",
      "scientificName": "Puntigrus tetrazona",
      "categoryGroup": "barb",
      "articleUrl": "https://www.practicalfishkeeping.co.uk/features/bring-on-the-barbs/",
      "imageUrl": null,
      "uniqueAngle": "PFK barb overview feature",
      "notes": null
    },
    {
      "commonName": "Cherry Barb",
      "scientificName": "Puntius titteya",
      "categoryGroup": "barb",
      "articleUrl": "https://www.practicalfishkeeping.co.uk/features/bring-on-the-barbs/",
      "imageUrl": null,
      "uniqueAngle": "PFK barb overview feature; UK community staple",
      "notes": null
    },
    {
      "commonName": "Odessa Barb",
      "scientificName": "Pethia padamya",
      "categoryGroup": "barb",
      "articleUrl": "https://www.practicalfishkeeping.co.uk/features/have-you-kept-these-five-underrated-barbs/",
      "imageUrl": null,
      "uniqueAngle": "PFK underrated barbs feature; UK trade species",
      "notes": null
    },
    {
      "commonName": "Harlequin Rasbora",
      "scientificName": "Trigonostigma heteromorpha",
      "categoryGroup": "rasbora",
      "articleUrl": "https://www.practicalfishkeeping.co.uk/features/a-guide-to-the-small-rasboras-from-the-genus-trigonostigma/",
      "imageUrl": null,
      "uniqueAngle": "PFK Trigonostigma genus guide; UK aquarium staple since 1930s",
      "notes": null
    },
    {
      "commonName": "Lambchop / Espe's Rasbora",
      "scientificName": "Trigonostigma espei",
      "categoryGroup": "rasbora",
      "articleUrl": "https://www.practicalfishkeeping.co.uk/features/a-guide-to-the-small-rasboras-from-the-genus-trigonostigma/",
      "imageUrl": null,
      "uniqueAngle": "PFK Trigonostigma genus guide",
      "notes": null
    },
    {
      "commonName": "Hengel's Rasbora",
      "scientificName": "Trigonostigma hengeli",
      "categoryGroup": "rasbora",
      "articleUrl": "https://www.practicalfishkeeping.co.uk/features/a-guide-to-the-small-rasboras-from-the-genus-trigonostigma/",
      "imageUrl": null,
      "uniqueAngle": "PFK Trigonostigma guide; smaller and less common than harlequin",
      "notes": null
    },
    {
      "commonName": "Chilli / Mosquito Rasbora",
      "scientificName": "Boraras brigittae",
      "categoryGroup": "rasbora",
      "articleUrl": "https://www.practicalfishkeeping.co.uk/features/chilli-rasbora-care-guide-boraras-brigittae/",
      "imageUrl": null,
      "uniqueAngle": "PFK dedicated care guide; UK nano tank flagship species",
      "notes": null
    },
    {
      "commonName": "Pygmy / Dwarf Rasbora",
      "scientificName": "Boraras maculatus",
      "categoryGroup": "rasbora",
      "articleUrl": "https://www.practicalfishkeeping.co.uk/features/boraras-marvels-in-miniature/",
      "imageUrl": null,
      "uniqueAngle": "PFK Boraras feature; UK nano staple",
      "notes": null
    },
    {
      "commonName": "Galaxy Rasbora / Celestial Pearl Danio",
      "scientificName": "Danio margaritatus",
      "categoryGroup": "danio",
      "articleUrl": "https://www.practicalfishkeeping.co.uk/features/celestial-pearl-danio-the-small-fish-that-made-it-big/",
      "imageUrl": null,
      "uniqueAngle": "PFK feature article; PFK covered the original import frenzy; UK trade sensation ca. 2006",
      "notes": "Also covered under old name Microrasbora sp. Galaxy and Celestichthys margaritatus"
    },
    {
      "commonName": "Somphong's Rasbora",
      "scientificName": "Trigonostigma somphongsi",
      "categoryGroup": "rasbora",
      "articleUrl": "https://www.practicalfishkeeping.co.uk/features/finding-the-endangered-somphongs-rasbora/",
      "imageUrl": null,
      "uniqueAngle": "PFK field-trip feature; critically endangered, UK conservation angle",
      "notes": "Rare in trade globally; PFK wildlife/hobby conservation crossover piece"
    },
    {
      "commonName": "Yellowtail Rasbora",
      "scientificName": "Rasbora tornieri",
      "categoryGroup": "rasbora",
      "articleUrl": "https://www.practicalfishkeeping.co.uk/features/yellowtail-rasbora-rasbora-tornieri/",
      "imageUrl": null,
      "uniqueAngle": "PFK dedicated species profile",
      "notes": null
    },
    {
      "commonName": "Dwarf Danio",
      "scientificName": "Danio nigrofasciatus",
      "categoryGroup": "danio",
      "articleUrl": "https://www.practicalfishkeeping.co.uk/features/the-dwarf-danio-danio-nigrofasciatus/",
      "imageUrl": null,
      "uniqueAngle": "PFK dedicated species profile; northern Myanmar origin",
      "notes": null
    },
    {
      "commonName": "Panther Danio",
      "scientificName": "Danio aesculapii",
      "categoryGroup": "danio",
      "articleUrl": "https://www.practicalfishkeeping.co.uk/features/panther-danio-danio-aesculapii/",
      "imageUrl": null,
      "uniqueAngle": "PFK dedicated species profile; 2.5-3cm, UK nano import",
      "notes": null
    },
    {
      "commonName": "Glowlight Danio",
      "scientificName": "Danio choprae",
      "categoryGroup": "danio",
      "articleUrl": "https://www.practicalfishkeeping.co.uk/features/the-dwarf-danio-danio-nigrofasciatus/",
      "imageUrl": null,
      "uniqueAngle": "PFK species mention alongside Panther danio; UK trade nano species",
      "notes": null
    },
    {
      "commonName": "Zebrafish",
      "scientificName": "Danio rerio",
      "categoryGroup": "danio",
      "articleUrl": "https://www.practicalfishkeeping.co.uk/features/bring-on-the-barbs/",
      "imageUrl": null,
      "uniqueAngle": "UK beginner staple; PFK coverage across multiple features",
      "notes": null
    },
    {
      "commonName": "Neon Blue / Kubotai Rasbora",
      "scientificName": "Microdevario kubotai",
      "categoryGroup": "rasbora",
      "articleUrl": "https://www.practicalfishkeeping.co.uk/features/top-10-small-fish-for-nano-aquariums/",
      "imageUrl": null,
      "uniqueAngle": "PFK nano aquarium feature; subtle colouration noted for aquascaping",
      "notes": null
    },
    {
      "commonName": "Bronze Corydoras",
      "scientificName": "Corydoras aeneus",
      "categoryGroup": "corydoras",
      "articleUrl": "https://www.practicalfishkeeping.co.uk/features/focus-on-commonly-kept-corydoras/",
      "imageUrl": null,
      "uniqueAngle": "PFK commonly kept Corydoras focus; now reclassified as Osteogaster aeneus",
      "notes": "Type specimen for subfamily following Corydoradinae revision"
    },
    {
      "commonName": "Peppered Corydoras",
      "scientificName": "Corydoras paleatus",
      "categoryGroup": "corydoras",
      "articleUrl": "https://www.practicalfishkeeping.co.uk/features/focus-on-commonly-kept-corydoras/",
      "imageUrl": null,
      "uniqueAngle": "PFK commonly kept species; UK trade staple",
      "notes": null
    },
    {
      "commonName": "Sterba's Corydoras",
      "scientificName": "Corydoras sterbai",
      "categoryGroup": "corydoras",
      "articleUrl": "https://www.practicalfishkeeping.co.uk/features/focus-on-commonly-kept-corydoras/",
      "imageUrl": null,
      "uniqueAngle": "PFK second-most kept Corydoras by catfish keepers",
      "notes": null
    },
    {
      "commonName": "Pygmy Corydoras",
      "scientificName": "Gastrodermus pygmaeus",
      "categoryGroup": "corydoras",
      "articleUrl": "https://www.practicalfishkeeping.co.uk/features/the%20cute%20dwarf%20corydoras%20catfish/",
      "imageUrl": null,
      "uniqueAngle": "PFK dwarf Corydoras feature; nano tank recommendation",
      "notes": "Also referred to as Corydoras pygmaeus in older PFK articles"
    },
    {
      "commonName": "Hastatus Pygmy Corydoras",
      "scientificName": "Gastrodermus hastatus",
      "categoryGroup": "corydoras",
      "articleUrl": "https://www.practicalfishkeeping.co.uk/features/the%20cute%20dwarf%20corydoras%20catfish/",
      "imageUrl": null,
      "uniqueAngle": "PFK dwarf Corydoras feature",
      "notes": null
    },
    {
      "commonName": "Salt-and-Pepper Pygmy Corydoras",
      "scientificName": "Hoplisoma habrosum",
      "categoryGroup": "corydoras",
      "articleUrl": "https://www.practicalfishkeeping.co.uk/features/the%20cute%20dwarf%20corydoras%20catfish/",
      "imageUrl": null,
      "uniqueAngle": "PFK dwarf Corydoras feature",
      "notes": null
    },
    {
      "commonName": "Brochis / Emerald Catfish",
      "scientificName": "Brochis splendens",
      "categoryGroup": "corydoras",
      "articleUrl": "https://www.practicalfishkeeping.co.uk/features/brochis-a-giant-among-dwarfs/",
      "imageUrl": null,
      "uniqueAngle": "PFK dedicated feature 'Brochis: A giant among dwarfs'",
      "notes": "10-12 dorsal rays distinguishes from Corydoras"
    },
    {
      "commonName": "Common Pleco",
      "scientificName": "Pterygoplichthys pardalis",
      "categoryGroup": "pleco",
      "articleUrl": "https://www.practicalfishkeeping.co.uk/features/the-common-plec-a-big-problem/",
      "imageUrl": null,
      "uniqueAngle": "PFK 'big problem' cautionary article; tank size and adult care issues",
      "notes": null
    },
    {
      "commonName": "Bristlenose Pleco",
      "scientificName": "Ancistrus sp.",
      "categoryGroup": "pleco",
      "articleUrl": "https://www.practicalfishkeeping.co.uk/features/the-popular-plecos/",
      "imageUrl": null,
      "uniqueAngle": "PFK popular plecos feature; UK beginner catfish staple",
      "notes": null
    },
    {
      "commonName": "Otocinclus",
      "scientificName": "Otocinclus vittatus",
      "categoryGroup": "pleco",
      "articleUrl": "https://www.practicalfishkeeping.co.uk/features/keeping-otocinclus-catfish-in-the-aquarium/",
      "imageUrl": null,
      "uniqueAngle": "PFK dedicated care guide; most exported Otocinclus from Brazil",
      "notes": null
    },
    {
      "commonName": "Hypancistrus / Zebra Pleco",
      "scientificName": "Hypancistrus zebra",
      "categoryGroup": "pleco",
      "articleUrl": "https://www.practicalfishkeeping.co.uk/features/the-popular-plecos/",
      "imageUrl": null,
      "uniqueAngle": "PFK popular plecos feature; L046, high UK trade value",
      "notes": "8 described Hypancistrus species; about 50 known forms total"
    },
    {
      "commonName": "Rubber-lipped Pleco",
      "scientificName": "Chaetostoma milesi",
      "categoryGroup": "pleco",
      "articleUrl": "https://www.practicalfishkeeping.co.uk/fishkeeping-answers/which-pleco-suits-my-fish-tank/",
      "imageUrl": null,
      "uniqueAngle": "PFK pleco selection advice; UK trade algae eater",
      "notes": null
    },
    {
      "commonName": "Spiny Eel",
      "scientificName": "Mastacembelus armatus",
      "categoryGroup": "spiny-eel",
      "articleUrl": "https://www.practicalfishkeeping.co.uk/features/articles/mastacembelus-armatus",
      "imageUrl": null,
      "uniqueAngle": "PFK dedicated species profile; burrowing specialist",
      "notes": null
    },
    {
      "commonName": "Kuhli Loach",
      "scientificName": "Pangio semicincta",
      "categoryGroup": "loach",
      "articleUrl": "https://www.practicalfishkeeping.co.uk/features/articles/2017/2/2/set-up-a-kuhli-loach-hotel",
      "imageUrl": null,
      "uniqueAngle": "PFK dedicated setup guide; UK community bottom-dweller staple",
      "notes": null
    },
    {
      "commonName": "Clown Loach",
      "scientificName": "Chromobotia macracanthus",
      "categoryGroup": "loach",
      "articleUrl": "https://www.practicalfishkeeping.co.uk/features/quick-guide-to-loaches/",
      "imageUrl": null,
      "uniqueAngle": "PFK loach guide; UK trade top-seller",
      "notes": null
    },
    {
      "commonName": "Kubotai / Polka Dot Botia",
      "scientificName": "Botia kubotai",
      "categoryGroup": "loach",
      "articleUrl": "https://www.practicalfishkeeping.co.uk/features/articles/habitat-expert-botia-kubotai",
      "imageUrl": null,
      "uniqueAngle": "PFK habitat expert species feature; described 2004",
      "notes": null
    },
    {
      "commonName": "Crimson Loach",
      "scientificName": "Schistura sp. 'Crimson'",
      "categoryGroup": "loach",
      "articleUrl": "https://www.practicalfishkeeping.co.uk/features/crimson-loach-schistura-sp--crimson",
      "imageUrl": null,
      "uniqueAngle": "PFK dedicated profile; undescribed Schistura, UK import, gap-filler vs US resources",
      "notes": null
    },
    {
      "commonName": "Weather Loach / Dojo Loach",
      "scientificName": "Misgurnus anguillicaudatus",
      "categoryGroup": "loach",
      "articleUrl": "https://www.practicalfishkeeping.co.uk/features/weather-loaches-and-how-to-keep-them/",
      "imageUrl": null,
      "uniqueAngle": "PFK dedicated care guide; UK temperate/coldwater angle",
      "notes": null
    },
    {
      "commonName": "Hillstream Loach",
      "scientificName": "Sewellia lineolata",
      "categoryGroup": "hillstream-loach",
      "articleUrl": "https://www.practicalfishkeeping.co.uk/features/how-to-keep-hillstream-and-brook-loaches-in-the-aquarium/",
      "imageUrl": null,
      "uniqueAngle": "PFK dedicated hillstream/brook loach care guide; UK trade interest in fast-flow biotopes",
      "notes": null
    },
    {
      "commonName": "Liniparhomaloptera",
      "scientificName": "Liniparhomaloptera disparis disparis",
      "categoryGroup": "hillstream-loach",
      "articleUrl": "https://www.practicalfishkeeping.co.uk/features/articles/liniparhomaloptera-disparis-disparis",
      "imageUrl": null,
      "uniqueAngle": "PFK dedicated species profile; obscure hillstream species rarely in US trade",
      "notes": null
    },
    {
      "commonName": "Rhinogobius Goby",
      "scientificName": "Rhinogobius sp.",
      "categoryGroup": "goby",
      "articleUrl": "https://www.practicalfishkeeping.co.uk/features/how-to-keep-rhinogobius-gobies/",
      "imageUrl": null,
      "uniqueAngle": "PFK dedicated care guide; coldwater-capable Asian gobies, niche UK interest",
      "notes": null
    },
    {
      "commonName": "Freshwater Bumblebee Goby",
      "scientificName": "Brachygobius xanthomelas",
      "categoryGroup": "goby",
      "articleUrl": "https://www.practicalfishkeeping.co.uk/features/freshwater-bumblebee-goby-brachygobius-xanthomelas/",
      "imageUrl": null,
      "uniqueAngle": "PFK species profile; true freshwater species (distinct from brackish Brachygobius)",
      "notes": "From Cambodia, Indonesia, Malaysia, Singapore; one of few fully freshwater bumblebee gobies"
    },
    {
      "commonName": "Peacock Gudgeon",
      "scientificName": "Tateurndina ocellicauda",
      "categoryGroup": "goby",
      "articleUrl": "https://www.practicalfishkeeping.co.uk/fishkeeping-answers/can-i-breed-these-gobies/",
      "imageUrl": null,
      "uniqueAngle": "PFK species profile; New Guinea sleeper goby, UK nano/community fish",
      "notes": null
    },
    {
      "commonName": "Dwarf Gourami",
      "scientificName": "Trichogaster lalius",
      "categoryGroup": "gourami",
      "articleUrl": "https://www.practicalfishkeeping.co.uk/features/lets-hear-it-for-the-dwarf-gourami/",
      "imageUrl": null,
      "uniqueAngle": "PFK dedicated feature; UK trade flagship, iridovirus disease issue noted",
      "notes": null
    },
    {
      "commonName": "Sparkling Gourami",
      "scientificName": "Trichopsis pumila",
      "categoryGroup": "gourami",
      "articleUrl": "https://www.practicalfishkeeping.co.uk/features/everything-you-need-to-know-about-the-brilliantly-bright-sparkling-gou/",
      "imageUrl": null,
      "uniqueAngle": "PFK dedicated article; nano tank gourami, up to 4cm",
      "notes": null
    },
    {
      "commonName": "Honey Gourami",
      "scientificName": "Trichogaster chuna",
      "categoryGroup": "gourami",
      "articleUrl": "https://www.practicalfishkeeping.co.uk/fishkeeping-news/quick-guide-to-anabantoids/",
      "imageUrl": null,
      "uniqueAngle": "PFK anabantoid guide; popular UK community species",
      "notes": null
    },
    {
      "commonName": "Chocolate Gourami",
      "scientificName": "Sphaerichthys osphromenoides",
      "categoryGroup": "gourami",
      "articleUrl": "https://www.practicalfishkeeping.co.uk/features/chocolate-gouramis-explained-sphaerichthyscare-guide/",
      "imageUrl": null,
      "uniqueAngle": "PFK dedicated Sphaerichthys care guide; blackwater specialist, demanding UK species",
      "notes": null
    },
    {
      "commonName": "Liquorice Gourami",
      "scientificName": "Parosphromenus spp.",
      "categoryGroup": "gourami",
      "articleUrl": "https://www.practicalfishkeeping.co.uk/features/liquorice-gourami-the-best-fish-to-stock-in-your-blackwater-aquarium/",
      "imageUrl": null,
      "uniqueAngle": "PFK blackwater aquarium feature; multiple Parosphromenus species, peat swamp specialists",
      "notes": "Genus covers multiple UK-imported species; most do well as pairs in 20l"
    },
    {
      "commonName": "Eyespot Gourami",
      "scientificName": "Parasphaerichthys ocellatus",
      "categoryGroup": "gourami",
      "articleUrl": "https://www.practicalfishkeeping.co.uk/features/parasphaerichthys-ocellatus-eyespot-gourami/",
      "imageUrl": null,
      "uniqueAngle": "PFK dedicated species profile; unusual cooler-water gourami (18-24C), rare in US trade",
      "notes": null
    },
    {
      "commonName": "Siamese Fighting Fish",
      "scientificName": "Betta splendens",
      "categoryGroup": "betta",
      "articleUrl": "https://www.practicalfishkeeping.co.uk/fishkeeping-news/guidelines-released-for-keeping-fighters/",
      "imageUrl": null,
      "uniqueAngle": "PFK welfare guidelines article; UK trade flagship",
      "notes": null
    },
    {
      "commonName": "White-seam Betta",
      "scientificName": "Betta albimarginata",
      "categoryGroup": "betta",
      "articleUrl": "https://www.practicalfishkeeping.co.uk/features/betta-albimarginata-care-guide-how-to-keep-and-breed-the-white-seam-be/",
      "imageUrl": null,
      "uniqueAngle": "PFK dedicated care+breeding guide; mouthbrooding Betta from Borneo peat swamps",
      "notes": null
    },
    {
      "commonName": "Brunei Beauty Betta",
      "scientificName": "Betta macrostoma",
      "categoryGroup": "betta",
      "articleUrl": "https://www.practicalfishkeeping.co.uk/features/brunei-beauty-betta-macrostoma/",
      "imageUrl": null,
      "uniqueAngle": "PFK dedicated species profile; chunky 9-11cm Borneo mouthbrooder, UK conservation interest",
      "notes": null
    },
    {
      "commonName": "Sim's Betta",
      "scientificName": "Betta simorum",
      "categoryGroup": "betta",
      "articleUrl": "https://www.practicalfishkeeping.co.uk/features/sims-betta-betta-simorum/",
      "imageUrl": null,
      "uniqueAngle": "PFK dedicated species profile; wild Betta rarely seen in US trade",
      "notes": null
    },
    {
      "commonName": "Banded Gourami",
      "scientificName": "Trichogaster fasciata",
      "categoryGroup": "gourami",
      "articleUrl": "https://www.practicalfishkeeping.co.uk/fishkeeping-news/quick-guide-to-anabantoids/",
      "imageUrl": null,
      "uniqueAngle": "PFK anabantoid guide",
      "notes": null
    },
    {
      "commonName": "Thick-lipped Gourami",
      "scientificName": "Trichogaster labiosa",
      "categoryGroup": "gourami",
      "articleUrl": "https://www.practicalfishkeeping.co.uk/fishkeeping-news/quick-guide-to-anabantoids/",
      "imageUrl": null,
      "uniqueAngle": "PFK anabantoid guide",
      "notes": null
    },
    {
      "commonName": "Microctenopoma fasciolatum",
      "scientificName": "Microctenopoma fasciolatum",
      "categoryGroup": "bushfish",
      "articleUrl": "https://www.practicalfishkeeping.co.uk/features/microctenopoma-fasciolatum/",
      "imageUrl": null,
      "uniqueAngle": "PFK dedicated species profile; African labyrinth fish, rarely covered in US resources",
      "notes": null
    },
    {
      "commonName": "Guppy",
      "scientificName": "Poecilia reticulata",
      "categoryGroup": "livebearer",
      "articleUrl": "https://www.practicalfishkeeping.co.uk/features/how-to-breed-perfect-guppies/",
      "imageUrl": null,
      "uniqueAngle": "PFK dedicated breeding guide; UK selective breeding tradition",
      "notes": null
    },
    {
      "commonName": "Endler's Livebearer",
      "scientificName": "Poecilia wingei",
      "categoryGroup": "livebearer",
      "articleUrl": "https://www.practicalfishkeeping.co.uk/features/endlers-livebearers-are-nearly-all-hybrids/",
      "imageUrl": null,
      "uniqueAngle": "PFK investigative feature on hybridisation in trade stock",
      "notes": null
    },
    {
      "commonName": "Platy",
      "scientificName": "Xiphophorus maculatus",
      "categoryGroup": "livebearer",
      "articleUrl": "https://www.practicalfishkeeping.co.uk/features/quick-guide-to-livebearers/",
      "imageUrl": null,
      "uniqueAngle": "PFK livebearer guide; UK beginner staple",
      "notes": null
    },
    {
      "commonName": "Swordtail",
      "scientificName": "Xiphophorus helleri",
      "categoryGroup": "livebearer",
      "articleUrl": "https://www.practicalfishkeeping.co.uk/features/great-fish-swordtails/",
      "imageUrl": null,
      "uniqueAngle": "PFK dedicated swordtail feature",
      "notes": null
    },
    {
      "commonName": "Pygmy Swordtail",
      "scientificName": "Xiphophorus multilineatus",
      "categoryGroup": "livebearer",
      "articleUrl": "https://www.practicalfishkeeping.co.uk/features/articles/pygmy-swordtail-xiphophorus-multilineatus",
      "imageUrl": null,
      "uniqueAngle": "PFK dedicated species profile; small wild-type Xiphophorus, UK specialist interest",
      "notes": null
    },
    {
      "commonName": "San Marcos Redtail Splitfin (Goodeid)",
      "scientificName": "Xenotoca doadroi",
      "categoryGroup": "livebearer",
      "articleUrl": "https://www.practicalfishkeeping.co.uk/features/colourful-goodeids-san-marcos-redtail-splitfin/",
      "imageUrl": null,
      "uniqueAngle": "PFK colourful goodeids feature; critically endangered Mexican livebearer, UK conservation breeding",
      "notes": "Males have golden-yellow coloration; PFK notable for covering this UKAPS/conservation angle"
    },
    {
      "commonName": "Clown Killifish",
      "scientificName": "Epiplatys annulatus",
      "categoryGroup": "killifish",
      "articleUrl": "https://www.practicalfishkeeping.co.uk/features/clown-killifish-a-tiny-jewel-for-planted-nano-tanks/",
      "imageUrl": null,
      "uniqueAngle": "PFK dedicated nano tank guide; 3cm, West African surface killifish",
      "notes": null
    },
    {
      "commonName": "Egger's Killifish",
      "scientificName": "Nothobranchius eggersi",
      "categoryGroup": "killifish",
      "articleUrl": "https://www.practicalfishkeeping.co.uk/features/eggers-killifish-nothobranchius-eggersi/",
      "imageUrl": null,
      "uniqueAngle": "PFK dedicated species profile; annual killifish, UK specialist interest",
      "notes": null
    },
    {
      "commonName": "Lyretail Killifish",
      "scientificName": "Aphyosemion australe",
      "categoryGroup": "killifish",
      "articleUrl": "https://www.practicalfishkeeping.co.uk/features/get-started-with-killifish/",
      "imageUrl": null,
      "uniqueAngle": "PFK killifish starter guide; UK killifish association standby species",
      "notes": null
    },
    {
      "commonName": "Blue Gularis Killifish",
      "scientificName": "Fundulopanchax sjoestedti",
      "categoryGroup": "killifish",
      "articleUrl": "https://www.practicalfishkeeping.co.uk/features/why-dont-more-people-keep-killies/",
      "imageUrl": null,
      "uniqueAngle": "PFK killifish advocacy feature; switch spawner, UK BKA coverage",
      "notes": null
    },
    {
      "commonName": "Steel-blue Killifish",
      "scientificName": "Fundulopanchax gardneri",
      "categoryGroup": "killifish",
      "articleUrl": "https://www.practicalfishkeeping.co.uk/fishkeeping-answers/which-killifish-are-best-to-start-with/",
      "imageUrl": null,
      "uniqueAngle": "PFK beginner killifish recommendation; UK trade regular",
      "notes": null
    },
    {
      "commonName": "Volcano Killifish",
      "scientificName": "Oryzias woworae",
      "categoryGroup": "killifish",
      "articleUrl": "https://www.practicalfishkeeping.co.uk/features/volcano-killifish/",
      "imageUrl": null,
      "uniqueAngle": "PFK dedicated species profile; Indonesian nano killifish, recently described",
      "notes": null
    },
    {
      "commonName": "Procatopus",
      "scientificName": "Procatopus aberrans",
      "categoryGroup": "killifish",
      "articleUrl": "https://www.practicalfishkeeping.co.uk/store/back-issues/practical-fishkeeping/practical-fishkeeping-january-2023",
      "imageUrl": null,
      "uniqueAngle": "PFK January 2023 cover feature on this tiny West African lampeye killi; UK specialist gap-filler",
      "notes": null
    },
    {
      "commonName": "Boesemani Rainbowfish",
      "scientificName": "Melanotaenia boesemani",
      "categoryGroup": "rainbowfish",
      "articleUrl": "https://www.practicalfishkeeping.co.uk/features/the-75-most-colourful-fish/",
      "imageUrl": null,
      "uniqueAngle": "PFK 75 most colourful fish; iconic blue-front/yellow-back species",
      "notes": null
    },
    {
      "commonName": "Celebes Rainbowfish",
      "scientificName": "Marosatherina ladigesi",
      "categoryGroup": "rainbowfish",
      "articleUrl": "https://www.practicalfishkeeping.co.uk/features/heiko-bleher-discovers-rainbowfish-and-blue-eyes/",
      "imageUrl": null,
      "uniqueAngle": "PFK Heiko Bleher field discovery feature; Indonesian endemic, UK specialist interest",
      "notes": null
    },
    {
      "commonName": "Rainbow Shiner",
      "scientificName": "Notropis chrosomus",
      "categoryGroup": "coldwater-fish",
      "articleUrl": "https://www.practicalfishkeeping.co.uk/features/rainbow-shiner-notropsis-chrosomus/",
      "imageUrl": null,
      "uniqueAngle": "PFK dedicated species profile; North American temperate fish, UK coldwater tank niche",
      "notes": null
    },
    {
      "commonName": "Red Shiner",
      "scientificName": "Cyprinella lutrensis",
      "categoryGroup": "coldwater-fish",
      "articleUrl": "https://www.practicalfishkeeping.co.uk/features/red-shiner-cyprinella-lutrensis/",
      "imageUrl": null,
      "uniqueAngle": "PFK dedicated species profile; North American temperate species, unique UK angle",
      "notes": null
    },
    {
      "commonName": "Kribensis",
      "scientificName": "Pelvicachromis pulcher",
      "categoryGroup": "cichlid",
      "articleUrl": "https://www.practicalfishkeeping.co.uk/features/kribensis-the-river-rainbows/",
      "imageUrl": null,
      "uniqueAngle": "PFK dedicated feature; UK aquarium staple, regional variant coverage",
      "notes": null
    },
    {
      "commonName": "Green Kribensis",
      "scientificName": "Pelvicachromis sacrimontis",
      "categoryGroup": "cichlid",
      "articleUrl": "https://www.practicalfishkeeping.co.uk/features/green-kribensis-pelvicachromis-sacrimontis/",
      "imageUrl": null,
      "uniqueAngle": "PFK dedicated species profile; less common than P. pulcher in UK trade",
      "notes": null
    },
    {
      "commonName": "Pelvicachromis rubrolabiatus",
      "scientificName": "Pelvicachromis rubrolabiatus",
      "categoryGroup": "cichlid",
      "articleUrl": "https://www.practicalfishkeeping.co.uk/features/pelvicachromis-rubrolabiatus/",
      "imageUrl": null,
      "uniqueAngle": "PFK dedicated species profile; UK specialist import, rarely covered in US resources",
      "notes": null
    },
    {
      "commonName": "Kribensis Regional Variants",
      "scientificName": "Pelvicachromis taeniatus",
      "categoryGroup": "cichlid",
      "articleUrl": "https://www.practicalfishkeeping.co.uk/features/the-regional-variants-of-pelvicachromis-kribensis/",
      "imageUrl": null,
      "uniqueAngle": "PFK regional variant feature; multiple locality forms, UK specialist/specialist trade",
      "notes": null
    },
    {
      "commonName": "Apistogramma baenschi",
      "scientificName": "Apistogramma baenschi",
      "categoryGroup": "cichlid",
      "articleUrl": "https://www.practicalfishkeeping.co.uk/features/how-to-keep-apistogramma-baenschi/",
      "imageUrl": null,
      "uniqueAngle": "PFK dedicated keeping guide",
      "notes": null
    },
    {
      "commonName": "Inka 50 Apistogramma",
      "scientificName": "Apistogramma baenschi",
      "categoryGroup": "cichlid",
      "articleUrl": "https://www.practicalfishkeeping.co.uk/fishkeeping-news/the-king-of-dwarves-gets-a-name/",
      "imageUrl": null,
      "uniqueAngle": "PFK news piece on formal naming of Inka 50 / King of Dwarves",
      "notes": "Trade name 'Inka 50' formally described as A. baenschi"
    },
    {
      "commonName": "Discus",
      "scientificName": "Symphysodon aequifasciatus",
      "categoryGroup": "cichlid",
      "articleUrl": "https://www.practicalfishkeeping.co.uk/features/definitive-guide-to-discus-part-one/",
      "imageUrl": null,
      "uniqueAngle": "PFK definitive guide (two parts); UK flagship specialist species",
      "notes": null
    },
    {
      "commonName": "Angelfish",
      "scientificName": "Pterophyllum scalare",
      "categoryGroup": "cichlid",
      "articleUrl": "https://www.practicalfishkeeping.co.uk/features/keeping-and-breeding-angelfish-in-the-aquarium/",
      "imageUrl": null,
      "uniqueAngle": "PFK dedicated care and breeding guide",
      "notes": null
    },
    {
      "commonName": "Oscar",
      "scientificName": "Astronotus ocellatus",
      "categoryGroup": "cichlid",
      "articleUrl": "https://www.practicalfishkeeping.co.uk/features/definitive-guide-to-oscars/",
      "imageUrl": null,
      "uniqueAngle": "PFK definitive guide; large cichlid UK trade staple",
      "notes": null
    },
    {
      "commonName": "Nandopsis / Cuban Cichlid",
      "scientificName": "Nandopsis tetracanthus",
      "categoryGroup": "cichlid",
      "articleUrl": "https://www.practicalfishkeeping.co.uk/features/nandopsis-cichlasoma-tetracanthus/",
      "imageUrl": null,
      "uniqueAngle": "PFK dedicated species profile; Central American rarity in UK trade",
      "notes": null
    },
    {
      "commonName": "Pseudotropheus demasoni",
      "scientificName": "Pseudotropheus demasoni",
      "categoryGroup": "cichlid",
      "articleUrl": "https://www.practicalfishkeeping.co.uk/features/malawi-must-have-pseudotropheus-demasoni/",
      "imageUrl": null,
      "uniqueAngle": "PFK 'Malawi must-have' feature; compact mbuna for UK hobbyists",
      "notes": null
    },
    {
      "commonName": "Otopharynx lithobates",
      "scientificName": "Otopharynx lithobates",
      "categoryGroup": "cichlid",
      "articleUrl": "https://www.practicalfishkeeping.co.uk/features/otopharynx-lithobates-tanzania/",
      "imageUrl": null,
      "uniqueAngle": "PFK dedicated species profile; Lake Malawi hap",
      "notes": null
    },
    {
      "commonName": "Cyphotilapia frontosa",
      "scientificName": "Cyphotilapia frontosa",
      "categoryGroup": "cichlid",
      "articleUrl": "https://www.practicalfishkeeping.co.uk/features/quick-guide-to-tanganyikan-cichlids/",
      "imageUrl": null,
      "uniqueAngle": "PFK Tanganyika guide; iconic Lake Tanganyika species",
      "notes": null
    },
    {
      "commonName": "Neolamprologus pulcher / Princess Cichlid",
      "scientificName": "Neolamprologus pulcher",
      "categoryGroup": "cichlid",
      "articleUrl": "https://www.practicalfishkeeping.co.uk/features/quick-guide-to-tanganyikan-cichlids/",
      "imageUrl": null,
      "uniqueAngle": "PFK Tanganyika guide; cooperative breeder, UK specialist favourite",
      "notes": null
    },
    {
      "commonName": "Lemon Cichlid",
      "scientificName": "Neolamprologus leleupi",
      "categoryGroup": "cichlid",
      "articleUrl": "https://www.practicalfishkeeping.co.uk/features/the-75-most-colourful-fish/",
      "imageUrl": null,
      "uniqueAngle": "PFK 75 most colourful; bright yellow Lake Tanganyika species",
      "notes": null
    },
    {
      "commonName": "Rubricatochromis / Dwarf Jewel Cichlid",
      "scientificName": "Rubricatochromis exsul",
      "categoryGroup": "cichlid",
      "articleUrl": "https://www.practicalfishkeeping.co.uk/features/the-stunning-cichlid-of-lake-turkana/",
      "imageUrl": null,
      "uniqueAngle": "PFK dedicated profile; Lake Turkana endemic, UK gap-filler vs US resources",
      "notes": null
    },
    {
      "commonName": "Big-eye Cichlid",
      "scientificName": "Acaronia nassa",
      "categoryGroup": "cichlid",
      "articleUrl": "https://www.practicalfishkeeping.co.uk/features/articles/big-eye-cichlid-acaronia-nassa",
      "imageUrl": null,
      "uniqueAngle": "PFK dedicated species profile; unusual South American predator cichlid",
      "notes": null
    },
    {
      "commonName": "Crenicichla jurubi",
      "scientificName": "Crenicichla jurubi",
      "categoryGroup": "cichlid",
      "articleUrl": "https://www.practicalfishkeeping.co.uk/features/crenicichla-jurubi/",
      "imageUrl": null,
      "uniqueAngle": "PFK dedicated species profile; pike cichlid, UK specialist import",
      "notes": null
    },
    {
      "commonName": "Biotodoma cupido",
      "scientificName": "Biotodoma cupido",
      "categoryGroup": "cichlid",
      "articleUrl": "https://www.practicalfishkeeping.co.uk/features/frequently-asked-questions-on-south-american-cichlids/",
      "imageUrl": null,
      "uniqueAngle": "PFK South American cichlids FAQ; mild-mannered geophagine",
      "notes": null
    },
    {
      "commonName": "Silver Arowana",
      "scientificName": "Osteoglossum bicirrhosum",
      "categoryGroup": "arowana",
      "articleUrl": "https://www.practicalfishkeeping.co.uk/features/predators-south-american-arowana/",
      "imageUrl": null,
      "uniqueAngle": "PFK predator series; UK specialist large-fish trade",
      "notes": null
    },
    {
      "commonName": "Black Arowana",
      "scientificName": "Osteoglossum ferreirai",
      "categoryGroup": "arowana",
      "articleUrl": "https://www.practicalfishkeeping.co.uk/features/predators-south-american-arowana/",
      "imageUrl": null,
      "uniqueAngle": "PFK predator series; lesser-seen species compared to Silver arowana",
      "notes": null
    },
    {
      "commonName": "Red-bellied Piranha",
      "scientificName": "Pygocentrus nattereri",
      "categoryGroup": "piranha",
      "articleUrl": "https://www.practicalfishkeeping.co.uk/features/the-red-bellied-piranha-what-a-spoilsport/",
      "imageUrl": null,
      "uniqueAngle": "PFK dedicated feature; legal to keep in UK (unlike some territories), specialist species",
      "notes": null
    },
    {
      "commonName": "Freshwater Stingray",
      "scientificName": "Potamotrygon motoro",
      "categoryGroup": "stingray",
      "articleUrl": "https://www.practicalfishkeeping.co.uk/features/definitive-guide-to-south-american-freshwater-rays/",
      "imageUrl": null,
      "uniqueAngle": "PFK definitive guide; legal in UK trade, specialist large-tank species",
      "notes": null
    },
    {
      "commonName": "Black Ghost Knifefish",
      "scientificName": "Apteronotus albifrons",
      "categoryGroup": "knifefish",
      "articleUrl": "https://www.practicalfishkeeping.co.uk/features/predators-the-knifefishes/",
      "imageUrl": null,
      "uniqueAngle": "PFK knifefish predator feature; deep river-channel species, UK specialist",
      "notes": null
    },
    {
      "commonName": "Elephantnose Fish",
      "scientificName": "Gnathonemus petersii",
      "categoryGroup": "mormyrid",
      "articleUrl": "https://www.practicalfishkeeping.co.uk/features/definitive-guide-to-elephantnoses/",
      "imageUrl": null,
      "uniqueAngle": "PFK definitive guide; electric-sense specialist, requires careful UK care",
      "notes": null
    },
    {
      "commonName": "Clouded Archerfish",
      "scientificName": "Toxotes blythii",
      "categoryGroup": "archerfish",
      "articleUrl": "https://www.practicalfishkeeping.co.uk/features/clouded-archerfish-toxotes-blythii/",
      "imageUrl": null,
      "uniqueAngle": "PFK dedicated species profile; Burmese freshwater archerfish, rare UK import, gap vs US trade",
      "notes": "Freshwater only; restricted Burma origin; recently appeared on SE Asian export lists"
    },
    {
      "commonName": "Barca Snakehead",
      "scientificName": "Channa barca",
      "categoryGroup": "snakehead",
      "articleUrl": "https://www.practicalfishkeeping.co.uk/features/barca-snakehead-channa-barca/",
      "imageUrl": null,
      "uniqueAngle": "PFK dedicated profile; world's rarest snakehead, newsworthy UK import",
      "notes": null
    },
    {
      "commonName": "Ceylon Snakehead",
      "scientificName": "Channa orientalis",
      "categoryGroup": "snakehead",
      "articleUrl": "https://www.practicalfishkeeping.co.uk/features/breeding-the-ceylon-snakehead-channa-orientalis/",
      "imageUrl": null,
      "uniqueAngle": "PFK dedicated breeding article; dwarf snakehead legal in UK",
      "notes": null
    },
    {
      "commonName": "Channa pulchra",
      "scientificName": "Channa pulchra",
      "categoryGroup": "snakehead",
      "articleUrl": "https://www.practicalfishkeeping.co.uk/features/channa-pulchra/",
      "imageUrl": null,
      "uniqueAngle": "PFK dedicated species profile; recently described Myanmar dwarf snakehead",
      "notes": null
    },
    {
      "commonName": "Channa diplogramma",
      "scientificName": "Channa diplogramma",
      "categoryGroup": "snakehead",
      "articleUrl": "https://www.practicalfishkeeping.co.uk/features/channa-diplogramma/",
      "imageUrl": null,
      "uniqueAngle": "PFK dedicated species profile; Malabar coast India, rare UK import",
      "notes": null
    },
    {
      "commonName": "Kerala Five Stripe Snakehead",
      "scientificName": "Channa sp. 'Kerala Five Stripe'",
      "categoryGroup": "snakehead",
      "articleUrl": "https://www.practicalfishkeeping.co.uk/features/channa-sp--kerala-five-stripe",
      "imageUrl": null,
      "uniqueAngle": "PFK dedicated profile; undescribed species, UK niche import",
      "notes": null
    },
    {
      "commonName": "Hairy Puffer",
      "scientificName": "Tetraodon baileyi",
      "categoryGroup": "puffer",
      "articleUrl": "https://www.practicalfishkeeping.co.uk/features/tetraodon-baileyi-hairy-puffer-fish/",
      "imageUrl": null,
      "uniqueAngle": "PFK dedicated species profile; aggressive freshwater puffer, species-only tank",
      "notes": null
    },
    {
      "commonName": "Dwarf Pufferfish",
      "scientificName": "Carinotetraodon travancoricus",
      "categoryGroup": "puffer",
      "articleUrl": "https://www.practicalfishkeeping.co.uk/features/all-you-need-to-know-about-dwarf-pufferfish-and-how-to-keep-them/",
      "imageUrl": null,
      "uniqueAngle": "PFK dedicated how-to feature; true freshwater puffer, UK nano specialist",
      "notes": null
    },
    {
      "commonName": "Golden Puffer",
      "scientificName": "Auriglobus silus",
      "categoryGroup": "puffer",
      "articleUrl": "https://www.practicalfishkeeping.co.uk/features/golden-puffer-auriglobus-silus/",
      "imageUrl": null,
      "uniqueAngle": "PFK dedicated species profile; most aggressive freshwater puffer, species-only",
      "notes": null
    },
    {
      "commonName": "South American Puffer",
      "scientificName": "Colomesus asellus",
      "categoryGroup": "puffer",
      "articleUrl": "https://www.practicalfishkeeping.co.uk/features/a-guide-to-asian-pufferfish/",
      "imageUrl": null,
      "uniqueAngle": "PFK puffer guide; shoaling river puffer, requires strong flow",
      "notes": null
    },
    {
      "commonName": "Badis sp. Buxar",
      "scientificName": "Badis sp. 'Buxar'",
      "categoryGroup": "badis",
      "articleUrl": "https://www.practicalfishkeeping.co.uk/features/badis-sp--buxar/",
      "imageUrl": null,
      "uniqueAngle": "PFK dedicated species profile; undescribed Badis locality form, UK import",
      "notes": null
    },
    {
      "commonName": "Badis blosyrus",
      "scientificName": "Badis blosyrus",
      "categoryGroup": "badis",
      "articleUrl": "https://www.practicalfishkeeping.co.uk/features/badis-blosyrus/",
      "imageUrl": null,
      "uniqueAngle": "PFK dedicated species profile; larger Badis species up to 10cm",
      "notes": null
    },
    {
      "commonName": "Scarlet Badis",
      "scientificName": "Dario dario",
      "categoryGroup": "badis",
      "articleUrl": "https://www.practicalfishkeeping.co.uk/features/what-fish-can-i-keep-in-my-small-tank-top-six-fish-for-your-nano-aquar/",
      "imageUrl": null,
      "uniqueAngle": "PFK nano fish recommendation; tiny Indian species with strong UK trade presence",
      "notes": null
    },
    {
      "commonName": "Thai Chandid",
      "scientificName": "Parambassis wolffii",
      "categoryGroup": "glassfish",
      "articleUrl": "https://www.practicalfishkeeping.co.uk/features/parambassis-wolffii-thai-chandid",
      "imageUrl": null,
      "uniqueAngle": "PFK dedicated species profile; large glassfish from SE Asia, UK import",
      "notes": null
    },
    {
      "commonName": "Indo-Pacific Tarpon",
      "scientificName": "Megalops cyprinoides",
      "categoryGroup": "tarpon",
      "articleUrl": "https://www.practicalfishkeeping.co.uk/features/indo-pacific-tarpon-megalops-cyprinoides/",
      "imageUrl": null,
      "uniqueAngle": "PFK dedicated species profile; unusual freshwater/brackish UK specialist fish",
      "notes": null
    },
    {
      "commonName": "Devario sondhii",
      "scientificName": "Devario sondhii",
      "categoryGroup": "danio",
      "articleUrl": "https://www.practicalfishkeeping.co.uk/features/devario-sondhii/",
      "imageUrl": null,
      "uniqueAngle": "PFK dedicated species profile; large devario, sympatric with galaxy rasbora in Myanmar",
      "notes": null
    },
    {
      "commonName": "African Butterfly Fish",
      "scientificName": "Pantodon buchholzi",
      "categoryGroup": "butterfly-fish",
      "articleUrl": "https://www.practicalfishkeeping.co.uk/features/predators-the-butterfly-fish/",
      "imageUrl": null,
      "uniqueAngle": "PFK predator series; surface predator, unique morphology, UK specialist interest",
      "notes": null
    },
    {
      "commonName": "Polypterus / Bichir",
      "scientificName": "Polypterus senegalus",
      "categoryGroup": "bichir",
      "articleUrl": "https://www.practicalfishkeeping.co.uk/fishkeeping-news/polypterus-amazing-powers-of-regeneration/",
      "imageUrl": null,
      "uniqueAngle": "PFK species coverage; 17 species of Polypteridae; UK large-fish specialist",
      "notes": null
    }
  ]
}
